pyextoverlay.py
pyextoverlay-1.1.4.dist-info/WHEEL
pyextoverlay-1.1.4.dist-info/METADATA
pyextoverlay-1.1.4.dist-info/RECORD
